{
	"id": "944ea78a-4ada-4cf7-aa17-75f99a4da77b",
	"name": "Example API Mock Server",
	"values": [
		{
			"key": "url",
			"value": "Set this to a mock or real API service to test\n",
			"enabled": true
		},
		{
			"key": "ACCESS_TOKEN",
			"value": "SET_THIS_TO_THE_TOKEN_OF_THE_TEST_USER",
			"enabled": true
		},
		{
			"key": "test_example1_exampleField1_value",
			"value": "example one exampleField1 value",
			"enabled": true
		},
		{
			"key": "test_example2_exampleField1_value",
			"value": "example two exampleField1 value",
			"enabled": true
		},
		{
			"key": "test_example1_exampleField1_newValue",
			"value": "new example1Field value for first example",
			"enabled": true
		},
		{
			"key": "latencyTolerance",
			"value": "0",
			"enabled": true
		},
		{
			"key": "TOKEN_MISSING_SCOPES",
			"value": "A_TOKEN_MISSING_EXAMPLE_SCOPES",
			"enabled": true
		},
		{
			"key": "testEnvironment",
			"value": "mock",
			"enabled": true
		},
		{
			"key": "stub_firstExampleId",
			"value": "SERVER_ASSIGNED_ID_FOR_EXAMPLE_1",
			"enabled": true
		},
		{
			"key": "stub_orgID_of_test_user_1",
			"value": "TEST_USER_1_ORGID",
			"enabled": true
		},
		{
			"key": "stub_secondExampleId",
			"value": "SERVER_ASSIGNED_ID_FOR_EXAMPLE_2",
			"enabled": true
		},
		{
			"key": "test_organization_id",
			"value": "ID_OF_PARTNER_MANAGED_ORG",
			"enabled": true
		}
	],
	"_postman_variable_scope": "environment",
	"_postman_exported_at": "2019-12-02T15:31:45.415Z",
	"_postman_exported_using": "Postman/7.12.0"
}